passwordlib/__init__.py
passwordlib/config.py
passwordlib/analyzer/__init__.py
passwordlib/analyzer/analyzer.py
passwordlib/attr/__init__.py
passwordlib/attr/attribute_class.py
passwordlib/commonly_used/__init__.py
passwordlib/commonly_used/password-list.txt
passwordlib/commonly_used/verifier.py
passwordlib/util/__init__.py
passwordlib/util/dumping.py
passwordlib/util/functions.py
passwordlib/util/hashing.py
password_library-0.4.2.dist-info/LICENSE
password_library-0.4.2.dist-info/METADATA
password_library-0.4.2.dist-info/WHEEL
password_library-0.4.2.dist-info/top_level.txt
password_library-0.4.2.dist-info/RECORD
