Metadata-Version: 2.1
Name: password-library
Version: 0.4.2
Summary: utility library to verify, hash, compare and more for passwords
Home-page: https://github.com/PlayerG9/passwordlib-py/
Author: PlayerG9
License: MIT
Project-URL: Author Github, https://github.com/PlayerG9
Project-URL: Homepage, https://github.com/PlayerG9/passwordlib-py/
Project-URL: Bug Tracker, https://github.com/PlayerG9/passwordlib-py/issues
Classifier: Intended Audience :: Developers
Classifier: Intended Audience :: System Administrators
Classifier: License :: OSI Approved :: MIT License
Classifier: Natural Language :: English
Classifier: Operating System :: OS Independent
Classifier: Programming Language :: Python :: 3
Classifier: Programming Language :: Python :: 3 :: Only
Classifier: Programming Language :: Python :: 3.7
Classifier: Programming Language :: Python :: 3.8
Classifier: Programming Language :: Python :: 3.9
Classifier: Programming Language :: Python :: 3.10
Classifier: Programming Language :: Python :: 3.11
Classifier: Programming Language :: Python :: 3.12
Classifier: Programming Language :: Python :: 3.13
Classifier: Topic :: Security
Classifier: Topic :: Utilities
License-File: LICENSE
